LICENSE
README.md
pyproject.toml
setup.cfg
setup.py
src/forta_agent/__init__.py
src/forta_agent/alert.py
src/forta_agent/alert_event.py
src/forta_agent/alert_test.py
src/forta_agent/alerts_api.py
src/forta_agent/block.py
src/forta_agent/block_event.py
src/forta_agent/bloom_filter.py
src/forta_agent/bloom_filter_test.py
src/forta_agent/event_type.py
src/forta_agent/finding.py
src/forta_agent/jwt.py
src/forta_agent/jwt_test.py
src/forta_agent/label.py
src/forta_agent/labels_api.py
src/forta_agent/labels_api_test.py
src/forta_agent/network.py
src/forta_agent/receipt.py
src/forta_agent/trace.py
src/forta_agent/transaction.py
src/forta_agent/transaction_event.py
src/forta_agent/utils.py
src/ups_bot_utils.egg-info/PKG-INFO
src/ups_bot_utils.egg-info/SOURCES.txt
src/ups_bot_utils.egg-info/dependency_links.txt
src/ups_bot_utils.egg-info/requires.txt
src/ups_bot_utils.egg-info/top_level.txt