Metadata-Version: 2.1
Name: ups-bot-utils
Version: 0.1.0
Summary: Forta Agent Python SDK (fork)
Home-page: https://github.com/AhmadElsagheer/forta-agent-sdk
Project-URL: Source, https://github.com/AhmadElsagheer/forta-agent-sdk
Project-URL: Documentation, https://github.com/AhmadElsagheer/forta-agent-sdk/README.md
Classifier: Programming Language :: Python :: 3
Classifier: License :: OSI Approved :: MIT License
Classifier: Operating System :: OS Independent
Requires-Python: >=3.6
License-File: LICENSE
